[
    {
        "name": "Leeuwarden",
        "file": "leeuwarden.json"
    },
    {
        "name": "De Bilt",
        "file": "de_bilt.json"
    },
    {
        "name": "Groningen (Eelde)",
        "file": "groningen_eelde.json"
    },
    {
        "name": "Rotterdam",
        "file": "rotterdam.json"
    },
    {
        "name": "Vlissingen",
        "file": "vlissingen.json"
    },
    {
        "name": "Twenthe",
        "file": "twenthe.json"
    },
    {
        "name": "Eindhoven",
        "file": "eindhoven.json"
    },
    {
        "name": "Hoogeveen",
        "file": "hoogeveen.json"
    }
]